{"sections":{"main":{"type":"main-page","settings":{"show-main-page":false}},"16333384199b920f8f":{"type":"donation-box","blocks":{"16333384199b920f8f-0":{"type":"range","settings":{"title":1}},"16333384199b920f8f-1":{"type":"range","settings":{"title":2}},"16333384199b920f8f-2":{"type":"range","settings":{"title":3}},"80c0f581-d9c6-4065-bc75-621fe98e104c":{"type":"range","settings":{"title":1}},"c589178c-165b-45ba-bbaa-3331ac946fa4":{"type":"range","settings":{"title":2}},"7a1f7f30-69a6-4707-8385-78cfd48e7086":{"type":"range","settings":{"title":4}},"13b539db-757a-4e64-9981-0ebe03bc7ec2":{"type":"range","settings":{"title":4}}},"block_order":["16333384199b920f8f-0","16333384199b920f8f-1","16333384199b920f8f-2","80c0f581-d9c6-4065-bc75-621fe98e104c","c589178c-165b-45ba-bbaa-3331ac946fa4","7a1f7f30-69a6-4707-8385-78cfd48e7086","13b539db-757a-4e64-9981-0ebe03bc7ec2"],"settings":{"title":"Fièra Customers<br class=\"hide-mob\"> Are Making A Difference!","sub_title":"With every purchase, we automatically donate a meal to a person in need.","desktop_image":"shopify:\/\/shop_images\/s2-brnd-img_550X_82efa2c8-d48a-44be-ad82-301c73fd98c2.png","mobile_image":"shopify:\/\/shop_images\/s2-brnd-img_550X_82efa2c8-d48a-44be-ad82-301c73fd98c2.png","donation_title":"Meals Donated By Fiera So Far","custom_html":""}}},"order":["main","16333384199b920f8f"]}